is_furry.py
src/__init__.py
is_furry_py-1.1.0.dist-info/METADATA
is_furry_py-1.1.0.dist-info/WHEEL
is_furry_py-1.1.0.dist-info/licenses/LICENSE
is_furry_py-1.1.0.dist-info/RECORD
