Metadata-Version: 2.1
Name: is-furry-py
Version: 1.1.0
Summary: Returns True if a string contains a variation of 'OwO'
Project-URL: Homepage, https://github.com/bunniico/is-furry-py
Project-URL: Bug Tracker, https://github.com/wait-what/is-furry/issues
Project-URL: Blog, https://hawkuarine.wordpress.com/
Author-email: EllieR <fellhawkstudios@gmail.com>
License-File: LICENSE
Classifier: License :: OSI Approved :: MIT License
Classifier: Operating System :: OS Independent
Classifier: Programming Language :: Python :: 3
Requires-Python: >3.0
